monviso_reloaded/PDB_manager.py
monviso_reloaded/__init__.py
monviso_reloaded/__main__.py
monviso_reloaded/analyzer.py
monviso_reloaded/base.py
monviso_reloaded/cli.py
monviso_reloaded/cobalt_wrapper.py
monviso_reloaded/database_parser.py
monviso_reloaded/file_handler.py
monviso_reloaded/gene.py
monviso_reloaded/input_parser.py
monviso_reloaded/isoform.py
monviso_reloaded/modeller_manager.py
monviso_reloaded/template.py
monviso-0.1.5.dist-info/LICENSE
monviso-0.1.5.dist-info/METADATA
monviso-0.1.5.dist-info/WHEEL
monviso-0.1.5.dist-info/entry_points.txt
monviso-0.1.5.dist-info/top_level.txt
monviso-0.1.5.dist-info/RECORD
