Metadata-Version: 2.1
Name: monviso
Version: 0.1.5
Summary: MoNvIso is a comprehensive software tool designed for the analysis and modeling of protein isoforms. It automates the process of identifying canonical and additional isoforms, assessing their modeling propensity, mapping mutations accurately, and building structural models of proteins.
Home-page: https://github.com/alisamalb/monviso_reloaded
Author: S. Albani
License: UNKNOWN
Platform: UNKNOWN
Requires-Python: >=3.9
License-File: LICENSE
Requires-Dist: biopython
Requires-Dist: pathlib
Requires-Dist: numpy
Requires-Dist: requests
Requires-Dist: torch
Requires-Dist: torchvision
Requires-Dist: torchaudio
Requires-Dist: scipy
Requires-Dist: scikit-learn
Requires-Dist: h5py
Requires-Dist: tqdm
Requires-Dist: gemmi
Requires-Dist: pandas
Requires-Dist: tensorboard
Provides-Extra: test
Requires-Dist: pytest ; extra == 'test'
Requires-Dist: coverage ; extra == 'test'
Requires-Dist: flake8 ; extra == 'test'
Requires-Dist: black ; extra == 'test'
Requires-Dist: isort ; extra == 'test'
Requires-Dist: pytest-cov ; extra == 'test'
Requires-Dist: mypy ; extra == 'test'
Requires-Dist: gitchangelog ; extra == 'test'
Requires-Dist: mkdocs ; extra == 'test'
Requires-Dist: mkdocstrings ; extra == 'test'
